requests_srv.py
setup.py
requests_srv.egg-info/PKG-INFO
requests_srv.egg-info/SOURCES.txt
requests_srv.egg-info/dependency_links.txt
requests_srv.egg-info/requires.txt
requests_srv.egg-info/top_level.txt