Metadata-Version: 1.1
Name: requests-srv
Version: 0.0.3
Summary: A wrapper for Requests supporting DNS SRV records.
Home-page: http://github.com/pstiasny/requests-srv
Author: Paweł Stiasny
Author-email: pawelstiasny@gmail.com
License: Apache 2.0
Keywords: requests
Platform: UNKNOWN
Classifier: Intended Audience :: Developers
Classifier: License :: OSI Approved :: Apache Software License
Classifier: Operating System :: OS Independent
Classifier: Programming Language :: Python :: 2
Classifier: Programming Language :: Python :: 2.7
